commentsremover/__init__.py
commentsremover/__main__.py
commentsremover-1.0.0.dist-info/LICENSE
commentsremover-1.0.0.dist-info/METADATA
commentsremover-1.0.0.dist-info/WHEEL
commentsremover-1.0.0.dist-info/top_level.txt
commentsremover-1.0.0.dist-info/RECORD
